mutwo/midi_converters/__init__.py
mutwo/midi_converters/backends.py
mutwo/midi_converters/configurations.py
mutwo/midi_converters/constants.py
mutwo/midi_converters/frontends.py
mutwo.ext_midi-0.7.3.dist-info/LICENSE
mutwo.ext_midi-0.7.3.dist-info/METADATA
mutwo.ext_midi-0.7.3.dist-info/WHEEL
mutwo.ext_midi-0.7.3.dist-info/top_level.txt
mutwo.ext_midi-0.7.3.dist-info/RECORD
