Metadata-Version: 2.1
Name: mutwo.ext-midi
Version: 0.7.3
Summary: midi extension for event based framework mutwo
Home-page: https://github.com/mutwo-org/mutwo.ext-midi
Author: Levin Eric Zimmermann
Author-email: levin.eric.zimmermann@posteo.eu
License: GPL
Project-URL: Documentation, https://mutwo.readthedocs.io/en/latest/
Platform: UNKNOWN
Requires-Python: >=3.9, <4
License-File: LICENSE
Requires-Dist: mutwo.ext-core (<0.60.0,>=0.58.0)
Requires-Dist: mutwo.ext-music (<0.17.0,>=0.11.0)
Requires-Dist: expenvelope (<1.0.0,>=0.6.5)
Requires-Dist: mido (<2,>=1.2.9)
Requires-Dist: numpy (<2.00,>=1.18)
Provides-Extra: testing
Requires-Dist: nose ; extra == 'testing'
Requires-Dist: coveralls ; extra == 'testing'
